flask_log_sku1/__init__.py
flask_log_sku1-1.1.3.dist-info/LICENSE
flask_log_sku1-1.1.3.dist-info/METADATA
flask_log_sku1-1.1.3.dist-info/WHEEL
flask_log_sku1-1.1.3.dist-info/entry_points.txt
flask_log_sku1-1.1.3.dist-info/top_level.txt
flask_log_sku1-1.1.3.dist-info/RECORD
