Metadata-Version: 2.1
Name: flask_log_sku1
Version: 1.1.3
Summary: Flask log output
Home-page: https://github.com/Skulldorom/flask_log_sku1
Author: Skulldorom
Author-email: Skulldorom@gmail.com
Project-URL: Bug Tracker, https://github.com/Skulldorom/flask_log_sku1
Classifier: Programming Language :: Python :: 3
Classifier: License :: OSI Approved :: MIT License
Classifier: Operating System :: OS Independent
Requires-Python: >=3.9
License-File: LICENSE
